passwordtest/PassCLI.py
passwordtest/__init__.py
passwordtest/__main__.py
passwordtest/main.py
passwordtest-1.2.dist-info/METADATA
passwordtest-1.2.dist-info/WHEEL
passwordtest-1.2.dist-info/entry_points.txt
passwordtest-1.2.dist-info/license.txt
passwordtest-1.2.dist-info/top_level.txt
passwordtest-1.2.dist-info/RECORD
