Metadata-Version: 2.1
Name: passwordtest
Version: 1.2
Summary: Password security measurement tool
Home-page: UNKNOWN
Author: alfiandecker2
Author-email: lcfhershell@tutanota.com
License: LcfherShell
Keywords: network,MITM
Platform: UNKNOWN
Requires-Python: >=2.7, !=3.0.*, !=3.1.*, !=3.2.*, !=3.3.*, <4
License-File: license.txt
